pssparser/__init__.py
pssparser/__main__.py
pssparser/cu_parser.py
pssparser/pssc.py
pssparser/antlr_gen/PSSLexer.py
pssparser/antlr_gen/PSSListener.py
pssparser/antlr_gen/PSSParser.py
pssparser/antlr_gen/PSSVisitor.py
pssparser/antlr_gen/__init__.py
pssparser/model/StmtBase.py
pssparser/model/__init__.py
pssparser/model/action_type.py
pssparser/model/activity.py
pssparser/model/activity_join_branch.py
pssparser/model/activity_join_first.py
pssparser/model/activity_join_none.py
pssparser/model/activity_join_select.py
pssparser/model/activity_stmt_base.py
pssparser/model/activity_stmt_bind.py
pssparser/model/activity_stmt_constraint.py
pssparser/model/activity_stmt_do_while.py
pssparser/model/activity_stmt_foreach.py
pssparser/model/activity_stmt_if_else.py
pssparser/model/activity_stmt_match.py
pssparser/model/activity_stmt_match_branch.py
pssparser/model/activity_stmt_parallel.py
pssparser/model/activity_stmt_repeat.py
pssparser/model/activity_stmt_replicate.py
pssparser/model/activity_stmt_schedule.py
pssparser/model/activity_stmt_scope.py
pssparser/model/activity_stmt_select.py
pssparser/model/activity_stmt_select_branch.py
pssparser/model/activity_stmt_sequence.py
pssparser/model/activity_stmt_super.py
pssparser/model/activity_stmt_traverse_handle.py
pssparser/model/activity_stmt_traverse_type.py
pssparser/model/activity_stmt_while.py
pssparser/model/attr_decl_stmt.py
pssparser/model/buffer_type.py
pssparser/model/compilation_unit.py
pssparser/model/compile_assert.py
pssparser/model/compile_if.py
pssparser/model/component_path.py
pssparser/model/component_path_elem.py
pssparser/model/component_type.py
pssparser/model/composite_stmt.py
pssparser/model/composite_type.py
pssparser/model/constraint_block.py
pssparser/model/constraint_declaration.py
pssparser/model/constraint_default.py
pssparser/model/constraint_default_disable.py
pssparser/model/constraint_expression.py
pssparser/model/constraint_forall.py
pssparser/model/constraint_foreach.py
pssparser-0.0.1.20200517.2.dist-info/LICENSE
pssparser-0.0.1.20200517.2.dist-info/METADATA
pssparser-0.0.1.20200517.2.dist-info/WHEEL
pssparser-0.0.1.20200517.2.dist-info/entry_points.txt
pssparser-0.0.1.20200517.2.dist-info/top_level.txt
pssparser-0.0.1.20200517.2.dist-info/RECORD
