Metadata-Version: 2.1
Name: pssparser
Version: 0.0.1.20200517.2
Summary: pssparser provides an Accellera PSS parser implemented with ANTLR and Python
Home-page: https://github.com/psstools/pssparser
Author: Matthew Ballance
Author-email: matt.ballance@gmail.com
License: Apache 2.0
Keywords: PSS,Portable Stimulus,Accellera
Platform: UNKNOWN
Requires-Dist: antlr4-python3-runtime
